MANIFEST.in
README.md
requirements.txt
setup.py
celery_opentracing/__init__.py
celery_opentracing/tracing.py
signalfx_instrumentation_celery.egg-info/PKG-INFO
signalfx_instrumentation_celery.egg-info/SOURCES.txt
signalfx_instrumentation_celery.egg-info/dependency_links.txt
signalfx_instrumentation_celery.egg-info/requires.txt
signalfx_instrumentation_celery.egg-info/top_level.txt