Metadata-Version: 2.1
Name: signalfx-instrumentation-celery
Version: 1.0.0
Summary: OpenTracing support for Celery
Home-page: http://github.com/signalfx/python-celery
Author: SignalFx, Inc.
Author-email: info@signalfx.com
License: Apache Software License v2
Download-URL: http://github.com/signalfx/python-celery/tarball/master
Platform: any
Classifier: Development Status :: 4 - Beta
Classifier: Intended Audience :: Developers
Classifier: Natural Language :: English
Classifier: License :: OSI Approved :: Apache Software License
Classifier: Programming Language :: Python
Classifier: Programming Language :: Python :: 2
Classifier: Programming Language :: Python :: 2.7
Classifier: Programming Language :: Python :: 3
Classifier: Programming Language :: Python :: 3.4
Classifier: Programming Language :: Python :: 3.5
Classifier: Programming Language :: Python :: 3.6
Classifier: Programming Language :: Python :: 3.7
Provides-Extra: unit_tests
Provides-Extra: integration_tests
